cogeno/__init__.py
cogeno/cogeno.py
cogeno/context.py
cogeno/error.py
cogeno/filelock.py
cogeno/generator.py
cogeno/importmodule.py
cogeno/include.py
cogeno/inlinegen.py
cogeno/jinja2gen.py
cogeno/lock.py
cogeno/log.py
cogeno/options.py
cogeno/output.py
cogeno/paths.py
cogeno/pygen.py
cogeno/redirectable.py
cogeno/stdmodules.py
cogeno/modules/__init__.py
cogeno/modules/ccode.py
cogeno/modules/cmake.py
cogeno/modules/config.py
cogeno/modules/doxygen.py
cogeno/modules/edts.py
cogeno/modules/protobuf.py
cogeno/modules/rstcode.py
cogeno/modules/zephyr.py
cogeno/modules/edtsdb/__init__.py
cogeno/modules/edtsdb/consumer.py
cogeno/modules/edtsdb/database.py
cogeno/modules/edtsdb/extractor.py
cogeno/modules/edtsdb/provider.py
cogeno/modules/edtsdb/dts/bindings/adc-controller.yaml
cogeno/modules/edtsdb/dts/bindings/base.yaml
cogeno/modules/edtsdb/dts/bindings/can-controller.yaml
cogeno/modules/edtsdb/dts/bindings/can-device.yaml
cogeno/modules/edtsdb/dts/bindings/chosen.yaml
cogeno/modules/edtsdb/dts/bindings/clock-consumer.yaml
cogeno/modules/edtsdb/dts/bindings/clock-controller.yaml
cogeno/modules/edtsdb/dts/bindings/cpu.yaml
cogeno/modules/edtsdb/dts/bindings/dma-client.yaml
cogeno/modules/edtsdb/dts/bindings/dma-controller.yaml
cogeno/modules/edtsdb/dts/bindings/eeprom-base.yaml
cogeno/modules/edtsdb/dts/bindings/eeprom-spi-i2c.yaml
cogeno/modules/edtsdb/dts/bindings/espi-controller.yaml
cogeno/modules/edtsdb/dts/bindings/ethernet.yaml
cogeno/modules/edtsdb/dts/bindings/fixed-clock.yaml
cogeno/modules/edtsdb/dts/bindings/fixed-partition.yaml
cogeno/modules/edtsdb/dts/bindings/flash-controller.yaml
cogeno/modules/edtsdb/dts/bindings/flash.yaml
cogeno/modules/edtsdb/dts/bindings/gpio-controller.yaml
cogeno/modules/edtsdb/dts/bindings/gpio-keys.yaml
cogeno/modules/edtsdb/dts/bindings/gpio-led.yaml
cogeno/modules/edtsdb/dts/bindings/gpio-leds.yaml
cogeno/modules/edtsdb/dts/bindings/gpio-nexus.yaml
cogeno/modules/edtsdb/dts/bindings/i2c-controller.yaml
cogeno-0.2.2.dist-info/LICENSE
cogeno-0.2.2.dist-info/METADATA
cogeno-0.2.2.dist-info/WHEEL
cogeno-0.2.2.dist-info/entry_points.txt
cogeno-0.2.2.dist-info/top_level.txt
cogeno-0.2.2.dist-info/RECORD
