Metadata-Version: 2.1
Name: cogeno
Version: 0.2.2
Summary: Inline code generation using Python or Jinja2 script snippets in any type of source file.
Home-page: https://gitlab.com/b0661/cogeno
Author: Bobby Noelte
Author-email: b0661n0e17e@gmail.com
License: Apache-2.0
Download-URL: https://gitlab.com/b0661/cogeno
Keywords: cogeno inline code generator embedded
Platform: any
Classifier: Development Status :: 3 - Alpha
Classifier: Environment :: Console
Classifier: Intended Audience :: Developers
Classifier: Intended Audience :: Education
Classifier: License :: OSI Approved :: Apache Software License
Classifier: Programming Language :: Python :: 3 :: Only
Classifier: Topic :: Software Development :: Code Generators
Classifier: Topic :: Software Development :: Embedded Systems
Classifier: Topic :: Utilities
Classifier: Operating System :: OS Independent
Requires-Python: >=3.6
Requires-Dist: Jinja2
Requires-Dist: pcpp
